[{"sequence":[{"type":"star","color":4294688548,"rotationDeg":0.0,"scale":0.8},{"type":"star","color":4294688548,"rotationDeg":0.0,"scale":0.8},{"type":"star","color":4294688548,"rotationDeg":0.0,"scale":0.8,"count":1,"layers":[{"type":"star","color":4294688548,"rotationDeg":0.0,"scale":0.8},{"type":"circle","color":4286680312,"rotationDeg":0.0,"scale":0.4}]},{"type":"star","color":4294688548,"rotationDeg":0.0,"scale":0.8,"count":1,"layers":[{"type":"star","color":4294688548,"rotationDeg":0.0,"scale":0.8},{"type":"circle","color":4292714717,"rotationDeg":0.0,"scale":0.4}]},{"type":"star","color":4294688548,"rotationDeg":0.0,"scale":0.8,"count":1,"layers":[{"type":"star","color":4294688548,"rotationDeg":0.0,"scale":0.8},{"type":"circle","color":4282759121,"rotationDeg":0.0,"scale":0.4},{"type":"pentagon","color":4294210230,"rotationDeg":0.0,"scale":0.4}]},{"type":"star","color":4294688548,"rotationDeg":0.0,"scale":0.8,"count":1,"layers":[{"type":"star","color":4294688548,"rotationDeg":0.0,"scale":0.8},{"type":"circle","color":4283354564,"rotationDeg":0.0,"scale":0.4},{"type":"pentagon","color":4294210230,"rotationDeg":0.0,"scale":0.4}]},{"type":"star","color":4294688548,"rotationDeg":0.0,"scale":0.8,"count":1,"layers":[{"type":"star","color":4294688548,"rotationDeg":0.0,"scale":0.8},{"type":"circle","color":4289170426,"rotationDeg":0.0,"scale":0.4},{"type":"pentagon","color":4284999929,"rotationDeg":0.0,"scale":0.4},{"type":"oval","color":4282759121,"rotationDeg":0.0,"scale":0.4}]},{"type":"star","color":4294688548,"rotationDeg":0.0,"scale":0.8,"count":1,"layers":[{"type":"star","color":4294688548,"rotationDeg":0.0,"scale":0.8},{"type":"circle","color":4294433903,"rotationDeg":0.0,"scale":0.4},{"type":"pentagon","color":4294677052,"rotationDeg":0.0,"scale":0.4},{"type":"oval","color":4288207048,"rotationDeg":0.0,"scale":0.4}]}],"options":[{"type":"hexagon","color":4294688548,"rotationDeg":0.0,"scale":0.8,"count":1,"layers":[{"type":"hexagon","color":4294688548,"rotationDeg":0.0,"scale":0.8},{"type":"pentagon","color":4294929259,"rotationDeg":0.0,"scale":0.4},{"type":"oval","color":4294472049,"rotationDeg":0.0,"scale":0.4}]},{"type":"pentagon","color":4294688548,"rotationDeg":0.0,"scale":0.8,"count":1,"layers":[{"type":"pentagon","color":4294688548,"rotationDeg":0.0,"scale":0.8},{"type":"triangle","color":4294929259,"rotationDeg":0.0,"scale":0.4},{"type":"star","color":4294472049,"rotationDeg":0.0,"scale":0.4}]},{"type":"star","color":4294929259,"rotationDeg":0.0,"scale":0.8,"count":1,"layers":[{"type":"star","color":4294929259,"rotationDeg":0.0,"scale":0.8},{"type":"circle","color":4286680312,"rotationDeg":0.0,"scale":0.4},{"type":"pentagon","color":4294472049,"rotationDeg":0.0,"scale":0.4}]},{"type":"star","color":4294688548,"rotationDeg":0.0,"scale":0.8,"count":1,"layers":[{"type":"star","color":4294688548,"rotationDeg":0.0,"scale":0.8},{"type":"circle","color":4294929259,"rotationDeg":0.0,"scale":0.4},{"type":"pentagon","color":4294472049,"rotationDeg":0.0,"scale":0.4}]},{"type":"square","color":4294433903,"rotationDeg":0.0,"scale":1.0},{"type":"star","color":4294688548,"rotationDeg":0.0,"scale":0.8}],"correctOptionIndex":5,"pattern":"additiveComposition","isMatrix":false,"id":"L30_Q1","level":30,"orderInLevel":1},{"sequence":[{"type":"pentagon","color":4288207048,"rotationDeg":0.0,"scale":0.5,"count":5,"layers":[{"type":"pentagon","color":4288207048,"rotationDeg":0.0,"scale":0.5}]},{"type":"pentagon","color":4288207048,"rotationDeg":0.0,"scale":0.62,"count":5,"layers":[{"type":"pentagon","color":4288207048,"rotationDeg":0.0,"scale":0.62}]},{"type":"pentagon","color":4288207048,"rotationDeg":0.0,"scale":0.74,"count":5,"layers":[{"type":"pentagon","color":4288207048,"rotationDeg":0.0,"scale":0.74}]},{"type":"pentagon","color":4288207048,"rotationDeg":0.0,"scale":0.86,"count":5,"layers":[{"type":"pentagon","color":4288207048,"rotationDeg":0.0,"scale":0.86}]},{"type":"pentagon","color":4288207048,"rotationDeg":0.0,"scale":0.98,"count":4,"layers":[{"type":"pentagon","color":4288207048,"rotationDeg":0.0,"scale":0.98}]},{"type":"pentagon","color":4288207048,"rotationDeg":0.0,"scale":1.1,"count":3,"layers":[{"type":"pentagon","color":4288207048,"rotationDeg":0.0,"scale":1.1}]},{"type":"pentagon","color":4288207048,"rotationDeg":0.0,"scale":1.22,"count":2,"layers":[{"type":"pentagon","color":4288207048,"rotationDeg":0.0,"scale":1.22}]},{"type":"pentagon","color":4288207048,"rotationDeg":0.0,"scale":1.3399999999999999}],"options":[{"type":"pentagon","color":4288207048,"rotationDeg":0.0,"scale":1.46},{"type":"pentagon","color":4286680312,"rotationDeg":0.0,"scale":1.0},{"type":"pentagon","color":4294677052,"rotationDeg":0.0,"scale":1.0},{"type":"oval","color":4282759121,"rotationDeg":0.0,"scale":1.0},{"type":"pentagon","color":4286767274,"rotationDeg":0.0,"scale":1.0,"linePattern":"horizontal"},{"type":"star","color":4283354564,"rotationDeg":0.0,"scale":1.0}],"correctOptionIndex":4,"pattern":"gridConvergence","isMatrix":false,"id":"L30_Q2","level":30,"orderInLevel":2},{"sequence":[{"type":"circle","color":4288073396,"rotationDeg":0.0,"scale":1.0},{"type":"square","color":4288073396,"rotationDeg":0.0,"scale":1.0},{"type":"triangle","color":4288073396,"rotationDeg":0.0,"scale":1.0},{"type":"pentagon","color":4288073396,"rotationDeg":0.0,"scale":1.0},{"type":"hexagon","color":4288073396,"rotationDeg":0.0,"scale":1.0},{"type":"oval","color":4288073396,"rotationDeg":0.0,"scale":1.0},{"type":"star","color":4288073396,"rotationDeg":0.0,"scale":1.0},{"type":"diamond","color":4288073396,"rotationDeg":0.0,"scale":1.0}],"options":[{"type":"circle","color":4289170426,"rotationDeg":0.0,"scale":1.0,"linePattern":"dot"},{"type":"circle","color":4281652121,"rotationDeg":0.0,"scale":1.0,"outlineOnly":true},{"type":"circle","color":4286767274,"rotationDeg":0.0,"scale":1.0},{"type":"circle","color":4283354564,"rotationDeg":0.0,"scale":1.0,"linePattern":"dot"},{"type":"circle","color":4286680312,"rotationDeg":0.0,"scale":1.0,"outlineOnly":true},{"type":"circle","color":4288073396,"rotationDeg":0.0,"scale":1.0}],"correctOptionIndex":3,"pattern":"shapeTypeProgression","isMatrix":false,"id":"L30_Q3","level":30,"orderInLevel":3},{"sequence":[{"type":"circle","color":4282759121,"rotationDeg":0.0,"scale":1.0},{"type":"circle","color":4282759121,"rotationDeg":45.0,"scale":1.0},{"type":"circle","color":4282759121,"rotationDeg":90.0,"scale":1.0,"outlineOnly":true},{"type":"circle","color":4282759121,"rotationDeg":135.0,"scale":1.0},{"type":"circle","color":4282759121,"rotationDeg":180.0,"scale":1.0},{"type":"circle","color":4282759121,"rotationDeg":225.0,"scale":1.0,"outlineOnly":true},{"type":"circle","color":4282759121,"rotationDeg":270.0,"scale":1.0},{"type":"circle","color":4282759121,"rotationDeg":315.0,"scale":1.0}],"options":[{"type":"circle","color":4294433903,"rotationDeg":0.0,"scale":1.0,"outlineOnly":true},{"type":"circle","color":4288207048,"rotationDeg":0.0,"scale":1.0,"linePattern":"dot"},{"type":"triangle","color":4294677052,"rotationDeg":0.0,"scale":1.0},{"type":"circle","color":4292714717,"rotationDeg":0.0,"scale":1.0,"outlineOnly":true},{"type":"circle","color":4281652121,"rotationDeg":0.0,"scale":1.0,"linePattern":"dot"},{"type":"circle","color":4282759121,"rotationDeg":360.0,"scale":1.0}],"correctOptionIndex":2,"pattern":"rotationOutlineCombo","isMatrix":false,"id":"L30_Q4","level":30,"orderInLevel":4},{"sequence":[{"type":"star","color":4282759121,"rotationDeg":0.0,"scale":0.7},{"type":"star","color":4292714717,"rotationDeg":0.0,"scale":1.1},{"type":"star","color":4282759121,"rotationDeg":0.0,"scale":0.7},{"type":"star","color":4292714717,"rotationDeg":0.0,"scale":1.1},{"type":"star","color":4282759121,"rotationDeg":0.0,"scale":0.7},{"type":"star","color":4292714717,"rotationDeg":0.0,"scale":1.1},{"type":"star","color":4282759121,"rotationDeg":0.0,"scale":0.7},{"type":"star","color":4292714717,"rotationDeg":0.0,"scale":1.1}],"options":[{"type":"star","color":4294677052,"rotationDeg":0.0,"scale":1.0},{"type":"star","color":4286680312,"rotationDeg":0.0,"scale":1.0,"linePattern":"horizontal"},{"type":"star","color":4286680312,"rotationDeg":0.0,"scale":1.0,"outlineOnly":true},{"type":"star","color":4282759121,"rotationDeg":0.0,"scale":0.7},{"type":"star","color":4294433903,"rotationDeg":0.0,"scale":1.0},{"type":"star","color":4282759121,"rotationDeg":0.0,"scale":1.0,"linePattern":"horizontal"}],"correctOptionIndex":1,"pattern":"colorScaleAlt","isMatrix":false,"id":"L30_Q5","level":30,"orderInLevel":5},{"sequence":[{"type":"oval","color":4294433903,"rotationDeg":0.0,"scale":0.8},{"type":"oval","color":4294433903,"rotationDeg":0.0,"scale":0.8},{"type":"oval","color":4294433903,"rotationDeg":0.0,"scale":0.8,"count":1,"layers":[{"type":"oval","color":4294433903,"rotationDeg":0.0,"scale":0.8},{"type":"star","color":4282759121,"rotationDeg":0.0,"scale":0.4}]},{"type":"oval","color":4294433903,"rotationDeg":0.0,"scale":0.8,"count":1,"layers":[{"type":"oval","color":4294433903,"rotationDeg":0.0,"scale":0.8},{"type":"star","color":4294677052,"rotationDeg":0.0,"scale":0.4}]},{"type":"oval","color":4294433903,"rotationDeg":0.0,"scale":0.8,"count":1,"layers":[{"type":"oval","color":4294433903,"rotationDeg":0.0,"scale":0.8},{"type":"star","color":4288073396,"rotationDeg":0.0,"scale":0.4},{"type":"circle","color":4294472049,"rotationDeg":0.0,"scale":0.4}]},{"type":"oval","color":4294433903,"rotationDeg":0.0,"scale":0.8,"count":1,"layers":[{"type":"oval","color":4294433903,"rotationDeg":0.0,"scale":0.8},{"type":"star","color":4281652121,"rotationDeg":0.0,"scale":0.4},{"type":"circle","color":4292714717,"rotationDeg":0.0,"scale":0.4}]},{"type":"oval","color":4294433903,"rotationDeg":0.0,"scale":0.8,"count":1,"layers":[{"type":"oval","color":4294433903,"rotationDeg":0.0,"scale":0.8},{"type":"star","color":4294677052,"rotationDeg":0.0,"scale":0.4},{"type":"circle","color":4294677052,"rotationDeg":0.0,"scale":0.4},{"type":"circle","color":4281652121,"rotationDeg":0.0,"scale":0.4}]},{"type":"oval","color":4294433903,"rotationDeg":0.0,"scale":0.8,"count":1,"layers":[{"type":"oval","color":4294433903,"rotationDeg":0.0,"scale":0.8},{"type":"star","color":4294688548,"rotationDeg":0.0,"scale":0.4},{"type":"circle","color":4284999929,"rotationDeg":0.0,"scale":0.4},{"type":"circle","color":4283354564,"rotationDeg":0.0,"scale":0.4}]}],"options":[{"type":"oval","color":4294433903,"rotationDeg":0.0,"scale":0.8},{"type":"triangle","color":4294433903,"rotationDeg":0.0,"scale":0.8,"count":1,"layers":[{"type":"triangle","color":4294433903,"rotationDeg":0.0,"scale":0.8},{"type":"star","color":4286767274,"rotationDeg":0.0,"scale":0.4},{"type":"pentagon","color":4294677052,"rotationDeg":0.0,"scale":0.4}]},{"type":"oval","color":4294433903,"rotationDeg":0.0,"scale":0.8,"count":1,"layers":[{"type":"oval","color":4294433903,"rotationDeg":0.0,"scale":0.8},{"type":"circle","color":4286767274,"rotationDeg":0.0,"scale":0.4},{"type":"pentagon","color":4294677052,"rotationDeg":0.0,"scale":0.4}]},{"type":"oval","color":4282759121,"rotationDeg":0.0,"scale":1.0},{"type":"diamond","color":4294688548,"rotationDeg":0.0,"scale":1.0},{"type":"oval","color":4294433903,"rotationDeg":0.0,"scale":0.8,"count":1,"layers":[{"type":"oval","color":4294433903,"rotationDeg":0.0,"scale":0.8},{"type":"star","color":4286767274,"rotationDeg":0.0,"scale":0.4},{"type":"circle","color":4294677052,"rotationDeg":0.0,"scale":0.4}]}],"correctOptionIndex":3,"pattern":"additiveComposition","isMatrix":false,"id":"L30_Q6","level":30,"orderInLevel":6},{"sequence":[{"type":"star","color":4283354564,"rotationDeg":0.0,"scale":0.5,"count":5,"layers":[{"type":"star","color":4283354564,"rotationDeg":0.0,"scale":0.5}]},{"type":"star","color":4283354564,"rotationDeg":0.0,"scale":0.62,"count":5,"layers":[{"type":"star","color":4283354564,"rotationDeg":0.0,"scale":0.62}]},{"type":"star","color":4283354564,"rotationDeg":0.0,"scale":0.74,"count":5,"layers":[{"type":"star","color":4283354564,"rotationDeg":0.0,"scale":0.74}]},{"type":"star","color":4283354564,"rotationDeg":0.0,"scale":0.86,"count":5,"layers":[{"type":"star","color":4283354564,"rotationDeg":0.0,"scale":0.86}]},{"type":"star","color":4283354564,"rotationDeg":0.0,"scale":0.98,"count":4,"layers":[{"type":"star","color":4283354564,"rotationDeg":0.0,"scale":0.98}]},{"type":"star","color":4283354564,"rotationDeg":0.0,"scale":1.1,"count":3,"layers":[{"type":"star","color":4283354564,"rotationDeg":0.0,"scale":1.1}]},{"type":"star","color":4283354564,"rotationDeg":0.0,"scale":1.22,"count":2,"layers":[{"type":"star","color":4283354564,"rotationDeg":0.0,"scale":1.22}]},{"type":"star","color":4283354564,"rotationDeg":0.0,"scale":1.3399999999999999}],"options":[{"type":"star","color":4288207048,"rotationDeg":0.0,"scale":1.0,"outlineOnly":true},{"type":"triangle","color":4283354564,"rotationDeg":0.0,"scale":1.0},{"type":"square","color":4283354564,"rotationDeg":0.0,"scale":1.0},{"type":"star","color":4283354564,"rotationDeg":0.0,"scale":1.0,"linePattern":"times"},{"type":"oval","color":4283354564,"rotationDeg":0.0,"scale":1.0},{"type":"star","color":4283354564,"rotationDeg":0.0,"scale":1.46}],"correctOptionIndex":4,"pattern":"gridConvergence","isMatrix":false,"id":"L30_Q7","level":30,"orderInLevel":7},{"sequence":[{"type":"circle","color":4283354564,"rotationDeg":0.0,"scale":1.0},{"type":"square","color":4283354564,"rotationDeg":0.0,"scale":1.0},{"type":"triangle","color":4283354564,"rotationDeg":0.0,"scale":1.0},{"type":"pentagon","color":4283354564,"rotationDeg":0.0,"scale":1.0},{"type":"hexagon","color":4283354564,"rotationDeg":0.0,"scale":1.0},{"type":"oval","color":4283354564,"rotationDeg":0.0,"scale":1.0},{"type":"star","color":4283354564,"rotationDeg":0.0,"scale":1.0},{"type":"diamond","color":4283354564,"rotationDeg":0.0,"scale":1.0}],"options":[{"type":"circle","color":4282759121,"rotationDeg":0.0,"scale":1.0,"outlineOnly":true},{"type":"circle","color":4283354564,"rotationDeg":0.0,"scale":1.0},{"type":"circle","color":4294677052,"rotationDeg":0.0,"scale":1.0},{"type":"square","color":4283354564,"rotationDeg":0.0,"scale":1.0},{"type":"circle","color":4292714717,"rotationDeg":0.0,"scale":1.0,"linePattern":"cross"},{"type":"circle","color":4286767274,"rotationDeg":0.0,"scale":1.0}],"correctOptionIndex":0,"pattern":"shapeTypeProgression","isMatrix":false,"id":"L30_Q8","level":30,"orderInLevel":8},{"sequence":[{"type":"circle","color":4294688548,"rotationDeg":0.0,"scale":1.0},{"type":"circle","color":4294688548,"rotationDeg":45.0,"scale":1.0},{"type":"circle","color":4294688548,"rotationDeg":90.0,"scale":1.0,"outlineOnly":true},{"type":"circle","color":4294688548,"rotationDeg":135.0,"scale":1.0},{"type":"circle","color":4294688548,"rotationDeg":180.0,"scale":1.0},{"type":"circle","color":4294688548,"rotationDeg":225.0,"scale":1.0,"outlineOnly":true},{"type":"circle","color":4294688548,"rotationDeg":270.0,"scale":1.0},{"type":"circle","color":4294688548,"rotationDeg":315.0,"scale":1.0}],"options":[{"type":"circle","color":4294472049,"rotationDeg":0.0,"scale":1.0,"linePattern":"horizontal"},{"type":"circle","color":4294688548,"rotationDeg":0.0,"scale":1.0,"outlineOnly":true},{"type":"pentagon","color":4294688548,"rotationDeg":0.0,"scale":1.0},{"type":"oval","color":4292714717,"rotationDeg":0.0,"scale":1.0},{"type":"circle","color":4294688548,"rotationDeg":360.0,"scale":1.0},{"type":"hexagon","color":4294688548,"rotationDeg":0.0,"scale":1.0}],"correctOptionIndex":1,"pattern":"rotationOutlineCombo","isMatrix":false,"id":"L30_Q9","level":30,"orderInLevel":9},{"sequence":[{"type":"square","color":4288207048,"rotationDeg":0.0,"scale":0.7},{"type":"square","color":4294472049,"rotationDeg":0.0,"scale":1.1},{"type":"square","color":4288207048,"rotationDeg":0.0,"scale":0.7},{"type":"square","color":4294472049,"rotationDeg":0.0,"scale":1.1},{"type":"square","color":4288207048,"rotationDeg":0.0,"scale":0.7},{"type":"square","color":4294472049,"rotationDeg":0.0,"scale":1.1},{"type":"square","color":4288207048,"rotationDeg":0.0,"scale":0.7},{"type":"square","color":4294472049,"rotationDeg":0.0,"scale":1.1}],"options":[{"type":"square","color":4286767274,"rotationDeg":0.0,"scale":1.0,"outlineOnly":true},{"type":"hexagon","color":4292714717,"rotationDeg":0.0,"scale":1.0},{"type":"square","color":4294688548,"rotationDeg":0.0,"scale":1.0,"linePattern":"dot"},{"type":"square","color":4288207048,"rotationDeg":0.0,"scale":0.7},{"type":"hexagon","color":4288207048,"rotationDeg":0.0,"scale":1.0},{"type":"square","color":4294677052,"rotationDeg":0.0,"scale":1.0,"outlineOnly":true}],"correctOptionIndex":4,"pattern":"colorScaleAlt","isMatrix":false,"id":"L30_Q10","level":30,"orderInLevel":10},{"sequence":[{"type":"star","color":4294210230,"rotationDeg":0.0,"scale":0.8},{"type":"star","color":4294210230,"rotationDeg":0.0,"scale":0.8},{"type":"star","color":4294210230,"rotationDeg":0.0,"scale":0.8,"count":1,"layers":[{"type":"star","color":4294210230,"rotationDeg":0.0,"scale":0.8},{"type":"triangle","color":4289170426,"rotationDeg":0.0,"scale":0.4}]},{"type":"star","color":4294210230,"rotationDeg":0.0,"scale":0.8,"count":1,"layers":[{"type":"star","color":4294210230,"rotationDeg":0.0,"scale":0.8},{"type":"triangle","color":4288073396,"rotationDeg":0.0,"scale":0.4}]},{"type":"star","color":4294210230,"rotationDeg":0.0,"scale":0.8,"count":1,"layers":[{"type":"star","color":4294210230,"rotationDeg":0.0,"scale":0.8},{"type":"triangle","color":4281652121,"rotationDeg":0.0,"scale":0.4},{"type":"triangle","color":4294677052,"rotationDeg":0.0,"scale":0.4}]},{"type":"star","color":4294210230,"rotationDeg":0.0,"scale":0.8,"count":1,"layers":[{"type":"star","color":4294210230,"rotationDeg":0.0,"scale":0.8},{"type":"triangle","color":4286767274,"rotationDeg":0.0,"scale":0.4},{"type":"triangle","color":4294210230,"rotationDeg":0.0,"scale":0.4}]},{"type":"star","color":4294210230,"rotationDeg":0.0,"scale":0.8,"count":1,"layers":[{"type":"star","color":4294210230,"rotationDeg":0.0,"scale":0.8},{"type":"triangle","color":4282759121,"rotationDeg":0.0,"scale":0.4},{"type":"triangle","color":4286680312,"rotationDeg":0.0,"scale":0.4},{"type":"diamond","color":4294677052,"rotationDeg":0.0,"scale":0.4}]},{"type":"star","color":4294210230,"rotationDeg":0.0,"scale":0.8,"count":1,"layers":[{"type":"star","color":4294210230,"rotationDeg":0.0,"scale":0.8},{"type":"triangle","color":4286767274,"rotationDeg":0.0,"scale":0.4},{"type":"triangle","color":4294929259,"rotationDeg":0.0,"scale":0.4},{"type":"diamond","color":4288207048,"rotationDeg":0.0,"scale":0.4}]}],"options":[{"type":"square","color":4294210230,"rotationDeg":0.0,"scale":0.8,"count":1,"layers":[{"type":"square","color":4294210230,"rotationDeg":0.0,"scale":0.8},{"type":"diamond","color":4294677052,"rotationDeg":0.0,"scale":0.4},{"type":"triangle","color":4283354564,"rotationDeg":0.0,"scale":0.4}]},{"type":"star","color":4294210230,"rotationDeg":0.0,"scale":0.8,"count":1,"layers":[{"type":"star","color":4294210230,"rotationDeg":0.0,"scale":0.8},{"type":"triangle","color":4294677052,"rotationDeg":0.0,"scale":0.4},{"type":"triangle","color":4283354564,"rotationDeg":0.0,"scale":0.4}]},{"type":"circle","color":4294210230,"rotationDeg":0.0,"scale":0.8,"count":1,"layers":[{"type":"circle","color":4294210230,"rotationDeg":0.0,"scale":0.8},{"type":"hexagon","color":4294677052,"rotationDeg":0.0,"scale":0.4},{"type":"circle","color":4283354564,"rotationDeg":0.0,"scale":0.4}]},{"type":"pentagon","color":4294210230,"rotationDeg":0.0,"scale":0.8,"count":1,"layers":[{"type":"pentagon","color":4294210230,"rotationDeg":0.0,"scale":0.8},{"type":"circle","color":4294677052,"rotationDeg":0.0,"scale":0.4},{"type":"pentagon","color":4283354564,"rotationDeg":0.0,"scale":0.4}]},{"type":"oval","color":4283354564,"rotationDeg":0.0,"scale":1.0},{"type":"star","color":4294210230,"rotationDeg":0.0,"scale":0.8}],"correctOptionIndex":2,"pattern":"additiveComposition","isMatrix":false,"id":"L30_Q11","level":30,"orderInLevel":11},{"sequence":[{"type":"diamond","color":4282759121,"rotationDeg":0.0,"scale":0.5,"count":5,"layers":[{"type":"diamond","color":4282759121,"rotationDeg":0.0,"scale":0.5}]},{"type":"diamond","color":4282759121,"rotationDeg":0.0,"scale":0.62,"count":5,"layers":[{"type":"diamond","color":4282759121,"rotationDeg":0.0,"scale":0.62}]},{"type":"diamond","color":4282759121,"rotationDeg":0.0,"scale":0.74,"count":5,"layers":[{"type":"diamond","color":4282759121,"rotationDeg":0.0,"scale":0.74}]},{"type":"diamond","color":4282759121,"rotationDeg":0.0,"scale":0.86,"count":5,"layers":[{"type":"diamond","color":4282759121,"rotationDeg":0.0,"scale":0.86}]},{"type":"diamond","color":4282759121,"rotationDeg":0.0,"scale":0.98,"count":4,"layers":[{"type":"diamond","color":4282759121,"rotationDeg":0.0,"scale":0.98}]},{"type":"diamond","color":4282759121,"rotationDeg":0.0,"scale":1.1,"count":3,"layers":[{"type":"diamond","color":4282759121,"rotationDeg":0.0,"scale":1.1}]},{"type":"diamond","color":4282759121,"rotationDeg":0.0,"scale":1.22,"count":2,"layers":[{"type":"diamond","color":4282759121,"rotationDeg":0.0,"scale":1.22}]},{"type":"diamond","color":4282759121,"rotationDeg":0.0,"scale":1.3399999999999999}],"options":[{"type":"star","color":4282759121,"rotationDeg":0.0,"scale":1.0},{"type":"diamond","color":4286680312,"rotationDeg":0.0,"scale":1.0,"linePattern":"times"},{"type":"diamond","color":4282759121,"rotationDeg":0.0,"scale":1.46},{"type":"diamond","color":4283354564,"rotationDeg":0.0,"scale":1.0,"linePattern":"dot"},{"type":"circle","color":4282759121,"rotationDeg":0.0,"scale":1.0},{"type":"hexagon","color":4282759121,"rotationDeg":0.0,"scale":1.0}],"correctOptionIndex":5,"pattern":"gridConvergence","isMatrix":false,"id":"L30_Q12","level":30,"orderInLevel":12},{"sequence":[{"type":"circle","color":4294210230,"rotationDeg":0.0,"scale":1.0},{"type":"square","color":4294210230,"rotationDeg":0.0,"scale":1.0},{"type":"triangle","color":4294210230,"rotationDeg":0.0,"scale":1.0},{"type":"pentagon","color":4294210230,"rotationDeg":0.0,"scale":1.0},{"type":"hexagon","color":4294210230,"rotationDeg":0.0,"scale":1.0},{"type":"oval","color":4294210230,"rotationDeg":0.0,"scale":1.0},{"type":"star","color":4294210230,"rotationDeg":0.0,"scale":1.0},{"type":"diamond","color":4294210230,"rotationDeg":0.0,"scale":1.0}],"options":[{"type":"circle","color":4282759121,"rotationDeg":0.0,"scale":1.0,"linePattern":"vertical"},{"type":"hexagon","color":4288207048,"rotationDeg":0.0,"scale":1.0},{"type":"star","color":4282759121,"rotationDeg":0.0,"scale":1.0},{"type":"circle","color":4294210230,"rotationDeg":0.0,"scale":1.0},{"type":"circle","color":4294929259,"rotationDeg":0.0,"scale":1.0,"linePattern":"cross"},{"type":"star","color":4294677052,"rotationDeg":0.0,"scale":1.0}],"correctOptionIndex":3,"pattern":"shapeTypeProgression","isMatrix":false,"id":"L30_Q13","level":30,"orderInLevel":13},{"sequence":[{"type":"star","color":4282759121,"rotationDeg":0.0,"scale":1.0},{"type":"star","color":4282759121,"rotationDeg":45.0,"scale":1.0},{"type":"star","color":4282759121,"rotationDeg":90.0,"scale":1.0,"outlineOnly":true},{"type":"star","color":4282759121,"rotationDeg":135.0,"scale":1.0},{"type":"star","color":4282759121,"rotationDeg":180.0,"scale":1.0},{"type":"star","color":4282759121,"rotationDeg":225.0,"scale":1.0,"outlineOnly":true},{"type":"star","color":4282759121,"rotationDeg":270.0,"scale":1.0},{"type":"star","color":4282759121,"rotationDeg":315.0,"scale":1.0}],"options":[{"type":"square","color":4281652121,"rotationDeg":0.0,"scale":1.0},{"type":"diamond","color":4282759121,"rotationDeg":0.0,"scale":1.0},{"type":"triangle","color":4282759121,"rotationDeg":0.0,"scale":1.0},{"type":"star","color":4282759121,"rotationDeg":360.0,"scale":1.0},{"type":"star","color":4282759121,"rotationDeg":0.0,"scale":1.0,"linePattern":"dot"},{"type":"star","color":4282759121,"rotationDeg":0.0,"scale":1.0}],"correctOptionIndex":3,"pattern":"rotationOutlineCombo","isMatrix":false,"id":"L30_Q14","level":30,"orderInLevel":14},{"sequence":[{"type":"diamond","color":4288073396,"rotationDeg":0.0,"scale":0.7},{"type":"diamond","color":4289170426,"rotationDeg":0.0,"scale":1.1},{"type":"diamond","color":4288073396,"rotationDeg":0.0,"scale":0.7},{"type":"diamond","color":4289170426,"rotationDeg":0.0,"scale":1.1},{"type":"diamond","color":4288073396,"rotationDeg":0.0,"scale":0.7},{"type":"diamond","color":4289170426,"rotationDeg":0.0,"scale":1.1},{"type":"diamond","color":4288073396,"rotationDeg":0.0,"scale":0.7},{"type":"diamond","color":4289170426,"rotationDeg":0.0,"scale":1.1}],"options":[{"type":"diamond","color":4286767274,"rotationDeg":0.0,"scale":1.0},{"type":"diamond","color":4294677052,"rotationDeg":0.0,"scale":1.0},{"type":"star","color":4288073396,"rotationDeg":0.0,"scale":1.0},{"type":"diamond","color":4288073396,"rotationDeg":0.0,"scale":1.0},{"type":"diamond","color":4288073396,"rotationDeg":0.0,"scale":0.7},{"type":"diamond","color":4294929259,"rotationDeg":0.0,"scale":1.0,"linePattern":"times"}],"correctOptionIndex":4,"pattern":"colorScaleAlt","isMatrix":false,"id":"L30_Q15","level":30,"orderInLevel":15},{"sequence":[{"type":"diamond","color":4286767274,"rotationDeg":0.0,"scale":0.8},{"type":"diamond","color":4286767274,"rotationDeg":0.0,"scale":0.8},{"type":"diamond","color":4286767274,"rotationDeg":0.0,"scale":0.8,"count":1,"layers":[{"type":"diamond","color":4286767274,"rotationDeg":0.0,"scale":0.8},{"type":"hexagon","color":4294677052,"rotationDeg":0.0,"scale":0.4}]},{"type":"diamond","color":4286767274,"rotationDeg":0.0,"scale":0.8,"count":1,"layers":[{"type":"diamond","color":4286767274,"rotationDeg":0.0,"scale":0.8},{"type":"hexagon","color":4282759121,"rotationDeg":0.0,"scale":0.4}]},{"type":"diamond","color":4286767274,"rotationDeg":0.0,"scale":0.8,"count":1,"layers":[{"type":"diamond","color":4286767274,"rotationDeg":0.0,"scale":0.8},{"type":"hexagon","color":4284999929,"rotationDeg":0.0,"scale":0.4},{"type":"square","color":4294929259,"rotationDeg":0.0,"scale":0.4}]},{"type":"diamond","color":4286767274,"rotationDeg":0.0,"scale":0.8,"count":1,"layers":[{"type":"diamond","color":4286767274,"rotationDeg":0.0,"scale":0.8},{"type":"hexagon","color":4294929259,"rotationDeg":0.0,"scale":0.4},{"type":"square","color":4288207048,"rotationDeg":0.0,"scale":0.4}]},{"type":"diamond","color":4286767274,"rotationDeg":0.0,"scale":0.8,"count":1,"layers":[{"type":"diamond","color":4286767274,"rotationDeg":0.0,"scale":0.8},{"type":"hexagon","color":4282759121,"rotationDeg":0.0,"scale":0.4},{"type":"square","color":4294210230,"rotationDeg":0.0,"scale":0.4},{"type":"triangle","color":4294677052,"rotationDeg":0.0,"scale":0.4}]},{"type":"diamond","color":4286767274,"rotationDeg":0.0,"scale":0.8,"count":1,"layers":[{"type":"diamond","color":4286767274,"rotationDeg":0.0,"scale":0.8},{"type":"hexagon","color":4294433903,"rotationDeg":0.0,"scale":0.4},{"type":"square","color":4286680312,"rotationDeg":0.0,"scale":0.4},{"type":"triangle","color":4284999929,"rotationDeg":0.0,"scale":0.4}]}],"options":[{"type":"diamond","color":4286767274,"rotationDeg":0.0,"scale":0.8},{"type":"diamond","color":4294688548,"rotationDeg":0.0,"scale":0.8,"count":1,"layers":[{"type":"diamond","color":4294688548,"rotationDeg":0.0,"scale":0.8},{"type":"hexagon","color":4294929259,"rotationDeg":0.0,"scale":0.4},{"type":"square","color":4282759121,"rotationDeg":0.0,"scale":0.4}]},{"type":"triangle","color":4286767274,"rotationDeg":0.0,"scale":0.8,"count":1,"layers":[{"type":"triangle","color":4286767274,"rotationDeg":0.0,"scale":0.8},{"type":"diamond","color":4294929259,"rotationDeg":0.0,"scale":0.4},{"type":"diamond","color":4282759121,"rotationDeg":0.0,"scale":0.4}]},{"type":"diamond","color":4294929259,"rotationDeg":0.0,"scale":1.0},{"type":"diamond","color":4282759121,"rotationDeg":0.0,"scale":0.8,"count":1,"layers":[{"type":"diamond","color":4282759121,"rotationDeg":0.0,"scale":0.8},{"type":"hexagon","color":4294433903,"rotationDeg":0.0,"scale":0.4},{"type":"square","color":4288073396,"rotationDeg":0.0,"scale":0.4}]},{"type":"diamond","color":4286767274,"rotationDeg":0.0,"scale":0.8,"count":1,"layers":[{"type":"diamond","color":4286767274,"rotationDeg":0.0,"scale":0.8},{"type":"hexagon","color":4294929259,"rotationDeg":0.0,"scale":0.4},{"type":"square","color":4282759121,"rotationDeg":0.0,"scale":0.4}]}],"correctOptionIndex":0,"pattern":"additiveComposition","isMatrix":false,"id":"L30_Q16","level":30,"orderInLevel":16},{"sequence":[{"type":"diamond","color":4294677052,"rotationDeg":0.0,"scale":0.5,"count":5,"layers":[{"type":"diamond","color":4294677052,"rotationDeg":0.0,"scale":0.5}]},{"type":"diamond","color":4294677052,"rotationDeg":0.0,"scale":0.62,"count":5,"layers":[{"type":"diamond","color":4294677052,"rotationDeg":0.0,"scale":0.62}]},{"type":"diamond","color":4294677052,"rotationDeg":0.0,"scale":0.74,"count":5,"layers":[{"type":"diamond","color":4294677052,"rotationDeg":0.0,"scale":0.74}]},{"type":"diamond","color":4294677052,"rotationDeg":0.0,"scale":0.86,"count":5,"layers":[{"type":"diamond","color":4294677052,"rotationDeg":0.0,"scale":0.86}]},{"type":"diamond","color":4294677052,"rotationDeg":0.0,"scale":0.98,"count":4,"layers":[{"type":"diamond","color":4294677052,"rotationDeg":0.0,"scale":0.98}]},{"type":"diamond","color":4294677052,"rotationDeg":0.0,"scale":1.1,"count":3,"layers":[{"type":"diamond","color":4294677052,"rotationDeg":0.0,"scale":1.1}]},{"type":"diamond","color":4294677052,"rotationDeg":0.0,"scale":1.22,"count":2,"layers":[{"type":"diamond","color":4294677052,"rotationDeg":0.0,"scale":1.22}]},{"type":"diamond","color":4294677052,"rotationDeg":0.0,"scale":1.3399999999999999}],"options":[{"type":"diamond","color":4288207048,"rotationDeg":0.0,"scale":1.0,"outlineOnly":true},{"type":"pentagon","color":4294472049,"rotationDeg":0.0,"scale":1.0},{"type":"diamond","color":4286767274,"rotationDeg":0.0,"scale":1.0},{"type":"square","color":4294677052,"rotationDeg":0.0,"scale":1.0},{"type":"diamond","color":4294677052,"rotationDeg":0.0,"scale":1.46},{"type":"diamond","color":4282759121,"rotationDeg":0.0,"scale":1.0}],"correctOptionIndex":5,"pattern":"gridConvergence","isMatrix":false,"id":"L30_Q17","level":30,"orderInLevel":17},{"sequence":[{"type":"circle","color":4294210230,"rotationDeg":0.0,"scale":1.0},{"type":"square","color":4294210230,"rotationDeg":0.0,"scale":1.0},{"type":"triangle","color":4294210230,"rotationDeg":0.0,"scale":1.0},{"type":"pentagon","color":4294210230,"rotationDeg":0.0,"scale":1.0},{"type":"hexagon","color":4294210230,"rotationDeg":0.0,"scale":1.0},{"type":"oval","color":4294210230,"rotationDeg":0.0,"scale":1.0},{"type":"star","color":4294210230,"rotationDeg":0.0,"scale":1.0},{"type":"diamond","color":4294210230,"rotationDeg":0.0,"scale":1.0}],"options":[{"type":"circle","color":4286767274,"rotationDeg":0.0,"scale":1.0,"linePattern":"diagonal"},{"type":"triangle","color":4294210230,"rotationDeg":0.0,"scale":1.0},{"type":"circle","color":4283354564,"rotationDeg":0.0,"scale":1.0},{"type":"circle","color":4294210230,"rotationDeg":0.0,"scale":1.0},{"type":"circle","color":4294929259,"rotationDeg":0.0,"scale":1.0,"linePattern":"cross"},{"type":"circle","color":4284999929,"rotationDeg":0.0,"scale":1.0,"linePattern":"plus"}],"correctOptionIndex":1,"pattern":"shapeTypeProgression","isMatrix":false,"id":"L30_Q18","level":30,"orderInLevel":18},{"sequence":[{"type":"diamond","color":4294472049,"rotationDeg":0.0,"scale":1.0},{"type":"diamond","color":4294472049,"rotationDeg":45.0,"scale":1.0},{"type":"diamond","color":4294472049,"rotationDeg":90.0,"scale":1.0,"outlineOnly":true},{"type":"diamond","color":4294472049,"rotationDeg":135.0,"scale":1.0},{"type":"diamond","color":4294472049,"rotationDeg":180.0,"scale":1.0},{"type":"diamond","color":4294472049,"rotationDeg":225.0,"scale":1.0,"outlineOnly":true},{"type":"diamond","color":4294472049,"rotationDeg":270.0,"scale":1.0},{"type":"diamond","color":4294472049,"rotationDeg":315.0,"scale":1.0}],"options":[{"type":"diamond","color":4294472049,"rotationDeg":0.0,"scale":1.0,"outlineOnly":true},{"type":"diamond","color":4294472049,"rotationDeg":360.0,"scale":1.0},{"type":"diamond","color":4288207048,"rotationDeg":0.0,"scale":1.0,"outlineOnly":true},{"type":"diamond","color":4294210230,"rotationDeg":0.0,"scale":1.0},{"type":"diamond","color":4286680312,"rotationDeg":0.0,"scale":1.0},{"type":"diamond","color":4294688548,"rotationDeg":0.0,"scale":1.0,"linePattern":"times"}],"correctOptionIndex":2,"pattern":"rotationOutlineCombo","isMatrix":false,"id":"L30_Q19","level":30,"orderInLevel":19},{"sequence":[{"type":"diamond","color":4288207048,"rotationDeg":0.0,"scale":0.7},{"type":"diamond","color":4281652121,"rotationDeg":0.0,"scale":1.1},{"type":"diamond","color":4288207048,"rotationDeg":0.0,"scale":0.7},{"type":"diamond","color":4281652121,"rotationDeg":0.0,"scale":1.1},{"type":"diamond","color":4288207048,"rotationDeg":0.0,"scale":0.7},{"type":"diamond","color":4281652121,"rotationDeg":0.0,"scale":1.1},{"type":"diamond","color":4288207048,"rotationDeg":0.0,"scale":0.7},{"type":"diamond","color":4281652121,"rotationDeg":0.0,"scale":1.1}],"options":[{"type":"diamond","color":4294677052,"rotationDeg":0.0,"scale":1.0},{"type":"oval","color":4281652121,"rotationDeg":0.0,"scale":1.0},{"type":"diamond","color":4294929259,"rotationDeg":0.0,"scale":1.0,"outlineOnly":true},{"type":"diamond","color":4292714717,"rotationDeg":0.0,"scale":1.0,"linePattern":"vertical"},{"type":"diamond","color":4288207048,"rotationDeg":0.0,"scale":0.7},{"type":"diamond","color":4294472049,"rotationDeg":0.0,"scale":1.0,"linePattern":"dot"}],"correctOptionIndex":4,"pattern":"colorScaleAlt","isMatrix":false,"id":"L30_Q20","level":30,"orderInLevel":20}]